maintain/__init__.py
maintain/changelog.py
maintain/config.py
maintain/git.py
maintain/process.py
maintain/commands/__init__.py
maintain/commands/release.py
maintain/commands/repo.py
maintain/release/__init__.py
maintain/release/aggregate.py
maintain/release/base.py
maintain/release/c.py
maintain/release/changelog.py
maintain/release/cocoapods.py
maintain/release/gem.py
maintain/release/git_releaser.py
maintain/release/github.py
maintain/release/hooks.py
maintain/release/npm.py
maintain/release/python.py
maintain/release/version_file.py
tests/__init__.py
tests/test_changelog.py
tests/test_config.py
tests/utils.py
tests/commands/__init__.py
tests/commands/test_release.py
tests/commands/test_repo.py
tests/release/__init__.py
tests/release/test_aggregate.py
tests/release/test_bump_version.py
tests/release/test_c.py
tests/release/test_changelog.py
tests/release/test_cocoapods.py
tests/release/test_gem.py
tests/release/test_git.py
tests/release/test_github.py
tests/release/test_hooks.py
tests/release/test_npm.py
tests/release/test_python.py
tests/release/test_version_file.py
maintain-0.4.0.dist-info/LICENSE
maintain-0.4.0.dist-info/METADATA
maintain-0.4.0.dist-info/WHEEL
maintain-0.4.0.dist-info/entry_points.txt
maintain-0.4.0.dist-info/top_level.txt
maintain-0.4.0.dist-info/RECORD
